{
  "ticker": "INTC",
  "price": 47.18,
  "conviction": 49.7,
  "is_signal": false,
  "mtmdi_zscore": -1.026,
  "mtmdi_raw": 0.498,
  "mtmdi_direction": -0.655,
  "cascade_score": -0.136,
  "momentum_persistence": 0.255,
  "strength": 0.4965,
  "vol_21d_raw": 0.5902447644461595,
  "vol_21d": 59.0,
  "vol_regime": "high",
  "position_size": 0.0,
  "drawdown": -13.1,
  "position_in_range": 80.3,
  "returns": {
    "5d": 4.66,
    "10d": -1.68,
    "21d": 2.27,
    "63d": 26.02,
    "126d": 47.5,
    "252d": 66.68
  },
  "signals": {
    "mtmdi": false,
    "direction": false,
    "cascade": false,
    "momentum": false
  },
  "chart": [
    {
      "date": "2025-03-25",
      "price": 24.2
    },
    {
      "date": "2025-03-26",
      "price": 23.42
    },
    {
      "date": "2025-03-27",
      "price": 23.62
    },
    {
      "date": "2025-03-28",
      "price": 22.71
    },
    {
      "date": "2025-03-31",
      "price": 22.71
    },
    {
      "date": "2025-04-01",
      "price": 22.05
    },
    {
      "date": "2025-04-02",
      "price": 21.98
    },
    {
      "date": "2025-04-03",
      "price": 22.43
    },
    {
      "date": "2025-04-04",
      "price": 19.85
    },
    {
      "date": "2025-04-07",
      "price": 19.57
    },
    {
      "date": "2025-04-08",
      "price": 18.13
    },
    {
      "date": "2025-04-09",
      "price": 21.53
    },
    {
      "date": "2025-04-10",
      "price": 19.88
    },
    {
      "date": "2025-04-11",
      "price": 19.74
    },
    {
      "date": "2025-04-14",
      "price": 20.31
    },
    {
      "date": "2025-04-15",
      "price": 19.85
    },
    {
      "date": "2025-04-16",
      "price": 19.23
    },
    {
      "date": "2025-04-17",
      "price": 18.93
    },
    {
      "date": "2025-04-21",
      "price": 18.84
    },
    {
      "date": "2025-04-22",
      "price": 19.51
    },
    {
      "date": "2025-04-23",
      "price": 20.59
    },
    {
      "date": "2025-04-24",
      "price": 21.49
    },
    {
      "date": "2025-04-25",
      "price": 20.05
    },
    {
      "date": "2025-04-28",
      "price": 20.51
    },
    {
      "date": "2025-04-29",
      "price": 20.34
    },
    {
      "date": "2025-04-30",
      "price": 20.1
    },
    {
      "date": "2025-05-01",
      "price": 19.98
    },
    {
      "date": "2025-05-02",
      "price": 20.62
    },
    {
      "date": "2025-05-05",
      "price": 20.27
    },
    {
      "date": "2025-05-06",
      "price": 19.94
    },
    {
      "date": "2025-05-07",
      "price": 20.31
    },
    {
      "date": "2025-05-08",
      "price": 21.0
    },
    {
      "date": "2025-05-09",
      "price": 21.42
    },
    {
      "date": "2025-05-12",
      "price": 22.18
    },
    {
      "date": "2025-05-13",
      "price": 22.56
    },
    {
      "date": "2025-05-14",
      "price": 21.52
    },
    {
      "date": "2025-05-15",
      "price": 21.55
    },
    {
      "date": "2025-05-16",
      "price": 21.66
    },
    {
      "date": "2025-05-19",
      "price": 21.38
    },
    {
      "date": "2025-05-20",
      "price": 21.27
    },
    {
      "date": "2025-05-21",
      "price": 20.69
    },
    {
      "date": "2025-05-22",
      "price": 20.55
    },
    {
      "date": "2025-05-23",
      "price": 20.05
    },
    {
      "date": "2025-05-27",
      "price": 20.55
    },
    {
      "date": "2025-05-28",
      "price": 20.37
    },
    {
      "date": "2025-05-29",
      "price": 20.25
    },
    {
      "date": "2025-05-30",
      "price": 19.55
    },
    {
      "date": "2025-06-02",
      "price": 19.74
    },
    {
      "date": "2025-06-03",
      "price": 20.29
    },
    {
      "date": "2025-06-04",
      "price": 20.25
    },
    {
      "date": "2025-06-05",
      "price": 19.99
    },
    {
      "date": "2025-06-06",
      "price": 20.06
    },
    {
      "date": "2025-06-09",
      "price": 20.48
    },
    {
      "date": "2025-06-10",
      "price": 22.08
    },
    {
      "date": "2025-06-11",
      "price": 20.68
    },
    {
      "date": "2025-06-12",
      "price": 20.77
    },
    {
      "date": "2025-06-13",
      "price": 20.14
    },
    {
      "date": "2025-06-16",
      "price": 20.74
    },
    {
      "date": "2025-06-17",
      "price": 20.8
    },
    {
      "date": "2025-06-18",
      "price": 21.49
    },
    {
      "date": "2025-06-20",
      "price": 21.08
    },
    {
      "date": "2025-06-23",
      "price": 21.19
    },
    {
      "date": "2025-06-24",
      "price": 22.55
    },
    {
      "date": "2025-06-25",
      "price": 22.2
    },
    {
      "date": "2025-06-26",
      "price": 22.5
    },
    {
      "date": "2025-06-27",
      "price": 22.69
    },
    {
      "date": "2025-06-30",
      "price": 22.4
    },
    {
      "date": "2025-07-01",
      "price": 22.85
    },
    {
      "date": "2025-07-02",
      "price": 21.88
    },
    {
      "date": "2025-07-03",
      "price": 22.49
    },
    {
      "date": "2025-07-07",
      "price": 22.0
    },
    {
      "date": "2025-07-08",
      "price": 23.59
    },
    {
      "date": "2025-07-09",
      "price": 23.44
    },
    {
      "date": "2025-07-10",
      "price": 23.82
    },
    {
      "date": "2025-07-11",
      "price": 23.43
    },
    {
      "date": "2025-07-14",
      "price": 23.3
    },
    {
      "date": "2025-07-15",
      "price": 22.92
    },
    {
      "date": "2025-07-16",
      "price": 22.69
    },
    {
      "date": "2025-07-17",
      "price": 22.8
    },
    {
      "date": "2025-07-18",
      "price": 23.1
    },
    {
      "date": "2025-07-21",
      "price": 23.26
    },
    {
      "date": "2025-07-22",
      "price": 23.24
    },
    {
      "date": "2025-07-23",
      "price": 23.49
    },
    {
      "date": "2025-07-24",
      "price": 22.63
    },
    {
      "date": "2025-07-25",
      "price": 20.7
    },
    {
      "date": "2025-07-28",
      "price": 20.68
    },
    {
      "date": "2025-07-29",
      "price": 20.41
    },
    {
      "date": "2025-07-30",
      "price": 20.34
    },
    {
      "date": "2025-07-31",
      "price": 19.8
    },
    {
      "date": "2025-08-01",
      "price": 19.31
    },
    {
      "date": "2025-08-04",
      "price": 19.5
    },
    {
      "date": "2025-08-05",
      "price": 20.19
    },
    {
      "date": "2025-08-06",
      "price": 20.41
    },
    {
      "date": "2025-08-07",
      "price": 19.77
    },
    {
      "date": "2025-08-08",
      "price": 19.95
    },
    {
      "date": "2025-08-11",
      "price": 20.65
    },
    {
      "date": "2025-08-12",
      "price": 21.81
    },
    {
      "date": "2025-08-13",
      "price": 22.22
    },
    {
      "date": "2025-08-14",
      "price": 23.86
    },
    {
      "date": "2025-08-15",
      "price": 24.56
    },
    {
      "date": "2025-08-18",
      "price": 23.66
    },
    {
      "date": "2025-08-19",
      "price": 25.31
    },
    {
      "date": "2025-08-20",
      "price": 23.54
    },
    {
      "date": "2025-08-21",
      "price": 23.5
    },
    {
      "date": "2025-08-22",
      "price": 24.8
    },
    {
      "date": "2025-08-25",
      "price": 24.55
    },
    {
      "date": "2025-08-26",
      "price": 24.35
    },
    {
      "date": "2025-08-27",
      "price": 24.85
    },
    {
      "date": "2025-08-28",
      "price": 24.93
    },
    {
      "date": "2025-08-29",
      "price": 24.35
    },
    {
      "date": "2025-09-02",
      "price": 24.21
    },
    {
      "date": "2025-09-03",
      "price": 24.0
    },
    {
      "date": "2025-09-04",
      "price": 24.61
    },
    {
      "date": "2025-09-05",
      "price": 24.49
    },
    {
      "date": "2025-09-08",
      "price": 24.48
    },
    {
      "date": "2025-09-09",
      "price": 24.44
    },
    {
      "date": "2025-09-10",
      "price": 24.77
    },
    {
      "date": "2025-09-11",
      "price": 24.61
    },
    {
      "date": "2025-09-12",
      "price": 24.08
    },
    {
      "date": "2025-09-15",
      "price": 24.77
    },
    {
      "date": "2025-09-16",
      "price": 25.27
    },
    {
      "date": "2025-09-17",
      "price": 24.9
    },
    {
      "date": "2025-09-18",
      "price": 30.57
    },
    {
      "date": "2025-09-19",
      "price": 29.58
    },
    {
      "date": "2025-09-22",
      "price": 28.76
    },
    {
      "date": "2025-09-23",
      "price": 29.34
    },
    {
      "date": "2025-09-24",
      "price": 31.22
    },
    {
      "date": "2025-09-25",
      "price": 33.99
    },
    {
      "date": "2025-09-26",
      "price": 35.5
    },
    {
      "date": "2025-09-29",
      "price": 34.48
    },
    {
      "date": "2025-09-30",
      "price": 33.55
    },
    {
      "date": "2025-10-01",
      "price": 35.94
    },
    {
      "date": "2025-10-02",
      "price": 37.3
    },
    {
      "date": "2025-10-03",
      "price": 36.83
    },
    {
      "date": "2025-10-06",
      "price": 36.59
    },
    {
      "date": "2025-10-07",
      "price": 37.17
    },
    {
      "date": "2025-10-08",
      "price": 37.43
    },
    {
      "date": "2025-10-09",
      "price": 37.8
    },
    {
      "date": "2025-10-10",
      "price": 36.37
    },
    {
      "date": "2025-10-13",
      "price": 37.22
    },
    {
      "date": "2025-10-14",
      "price": 35.63
    },
    {
      "date": "2025-10-15",
      "price": 37.15
    },
    {
      "date": "2025-10-16",
      "price": 36.84
    },
    {
      "date": "2025-10-17",
      "price": 37.01
    },
    {
      "date": "2025-10-20",
      "price": 38.1
    },
    {
      "date": "2025-10-21",
      "price": 38.12
    },
    {
      "date": "2025-10-22",
      "price": 36.92
    },
    {
      "date": "2025-10-23",
      "price": 38.16
    },
    {
      "date": "2025-10-24",
      "price": 38.28
    },
    {
      "date": "2025-10-27",
      "price": 39.54
    },
    {
      "date": "2025-10-28",
      "price": 41.53
    },
    {
      "date": "2025-10-29",
      "price": 41.34
    },
    {
      "date": "2025-10-30",
      "price": 40.16
    },
    {
      "date": "2025-10-31",
      "price": 39.99
    },
    {
      "date": "2025-11-03",
      "price": 39.5
    },
    {
      "date": "2025-11-04",
      "price": 37.03
    },
    {
      "date": "2025-11-05",
      "price": 38.38
    },
    {
      "date": "2025-11-06",
      "price": 37.24
    },
    {
      "date": "2025-11-07",
      "price": 38.13
    },
    {
      "date": "2025-11-10",
      "price": 38.45
    },
    {
      "date": "2025-11-11",
      "price": 37.88
    },
    {
      "date": "2025-11-12",
      "price": 37.89
    },
    {
      "date": "2025-11-13",
      "price": 35.91
    },
    {
      "date": "2025-11-14",
      "price": 35.52
    },
    {
      "date": "2025-11-17",
      "price": 34.71
    },
    {
      "date": "2025-11-18",
      "price": 34.33
    },
    {
      "date": "2025-11-19",
      "price": 35.11
    },
    {
      "date": "2025-11-20",
      "price": 33.62
    },
    {
      "date": "2025-11-21",
      "price": 34.5
    },
    {
      "date": "2025-11-24",
      "price": 35.79
    },
    {
      "date": "2025-11-25",
      "price": 35.83
    },
    {
      "date": "2025-11-26",
      "price": 36.81
    },
    {
      "date": "2025-11-28",
      "price": 40.56
    },
    {
      "date": "2025-12-01",
      "price": 40.01
    },
    {
      "date": "2025-12-02",
      "price": 43.47
    },
    {
      "date": "2025-12-03",
      "price": 43.76
    },
    {
      "date": "2025-12-04",
      "price": 40.5
    },
    {
      "date": "2025-12-05",
      "price": 41.41
    },
    {
      "date": "2025-12-08",
      "price": 40.3
    },
    {
      "date": "2025-12-09",
      "price": 40.5
    },
    {
      "date": "2025-12-10",
      "price": 40.78
    },
    {
      "date": "2025-12-11",
      "price": 39.51
    },
    {
      "date": "2025-12-12",
      "price": 37.81
    },
    {
      "date": "2025-12-15",
      "price": 37.51
    },
    {
      "date": "2025-12-16",
      "price": 37.31
    },
    {
      "date": "2025-12-17",
      "price": 36.05
    },
    {
      "date": "2025-12-18",
      "price": 36.28
    },
    {
      "date": "2025-12-19",
      "price": 36.82
    },
    {
      "date": "2025-12-22",
      "price": 36.37
    },
    {
      "date": "2025-12-23",
      "price": 36.35
    },
    {
      "date": "2025-12-24",
      "price": 36.16
    },
    {
      "date": "2025-12-26",
      "price": 36.2
    },
    {
      "date": "2025-12-29",
      "price": 36.68
    },
    {
      "date": "2025-12-30",
      "price": 37.3
    },
    {
      "date": "2025-12-31",
      "price": 36.9
    },
    {
      "date": "2026-01-02",
      "price": 39.38
    },
    {
      "date": "2026-01-05",
      "price": 39.37
    },
    {
      "date": "2026-01-06",
      "price": 40.04
    },
    {
      "date": "2026-01-07",
      "price": 42.63
    },
    {
      "date": "2026-01-08",
      "price": 41.11
    },
    {
      "date": "2026-01-09",
      "price": 45.55
    },
    {
      "date": "2026-01-12",
      "price": 44.06
    },
    {
      "date": "2026-01-13",
      "price": 47.29
    },
    {
      "date": "2026-01-14",
      "price": 48.72
    },
    {
      "date": "2026-01-15",
      "price": 48.32
    },
    {
      "date": "2026-01-16",
      "price": 46.96
    },
    {
      "date": "2026-01-20",
      "price": 48.56
    },
    {
      "date": "2026-01-21",
      "price": 54.25
    },
    {
      "date": "2026-01-22",
      "price": 54.32
    },
    {
      "date": "2026-01-23",
      "price": 45.07
    },
    {
      "date": "2026-01-26",
      "price": 42.49
    },
    {
      "date": "2026-01-27",
      "price": 43.93
    },
    {
      "date": "2026-01-28",
      "price": 48.78
    },
    {
      "date": "2026-01-29",
      "price": 48.66
    },
    {
      "date": "2026-01-30",
      "price": 46.47
    },
    {
      "date": "2026-02-02",
      "price": 48.81
    },
    {
      "date": "2026-02-03",
      "price": 49.25
    },
    {
      "date": "2026-02-04",
      "price": 48.6
    },
    {
      "date": "2026-02-05",
      "price": 48.24
    },
    {
      "date": "2026-02-06",
      "price": 50.59
    },
    {
      "date": "2026-02-09",
      "price": 50.24
    },
    {
      "date": "2026-02-10",
      "price": 47.13
    },
    {
      "date": "2026-02-11",
      "price": 48.29
    },
    {
      "date": "2026-02-12",
      "price": 46.48
    },
    {
      "date": "2026-02-13",
      "price": 46.79
    },
    {
      "date": "2026-02-17",
      "price": 46.18
    },
    {
      "date": "2026-02-18",
      "price": 45.46
    },
    {
      "date": "2026-02-19",
      "price": 44.62
    },
    {
      "date": "2026-02-20",
      "price": 44.11
    },
    {
      "date": "2026-02-23",
      "price": 43.63
    },
    {
      "date": "2026-02-24",
      "price": 46.12
    },
    {
      "date": "2026-02-25",
      "price": 46.88
    },
    {
      "date": "2026-02-26",
      "price": 45.46
    },
    {
      "date": "2026-02-27",
      "price": 45.61
    },
    {
      "date": "2026-03-02",
      "price": 45.5
    },
    {
      "date": "2026-03-03",
      "price": 43.1
    },
    {
      "date": "2026-03-04",
      "price": 45.58
    },
    {
      "date": "2026-03-05",
      "price": 45.95
    },
    {
      "date": "2026-03-06",
      "price": 43.42
    },
    {
      "date": "2026-03-09",
      "price": 45.58
    },
    {
      "date": "2026-03-10",
      "price": 46.78
    },
    {
      "date": "2026-03-11",
      "price": 47.98
    },
    {
      "date": "2026-03-12",
      "price": 45.25
    },
    {
      "date": "2026-03-13",
      "price": 45.77
    },
    {
      "date": "2026-03-16",
      "price": 45.76
    },
    {
      "date": "2026-03-17",
      "price": 44.06
    },
    {
      "date": "2026-03-18",
      "price": 45.03
    },
    {
      "date": "2026-03-19",
      "price": 46.18
    },
    {
      "date": "2026-03-20",
      "price": 43.87
    },
    {
      "date": "2026-03-23",
      "price": 44.01
    },
    {
      "date": "2026-03-24",
      "price": 44.06
    },
    {
      "date": "2026-03-25",
      "price": 47.18
    }
  ],
  "mtmdi_history": [
    {
      "date": "2025-03-25",
      "value": 0.509
    },
    {
      "date": "2025-03-26",
      "value": -0.522
    },
    {
      "date": "2025-03-27",
      "value": -0.917
    },
    {
      "date": "2025-03-28",
      "value": -0.802
    },
    {
      "date": "2025-03-31",
      "value": -0.499
    },
    {
      "date": "2025-04-01",
      "value": -0.244
    },
    {
      "date": "2025-04-02",
      "value": -0.531
    },
    {
      "date": "2025-04-03",
      "value": -0.55
    },
    {
      "date": "2025-04-04",
      "value": -0.353
    },
    {
      "date": "2025-04-07",
      "value": -0.346
    },
    {
      "date": "2025-04-08",
      "value": 0.049
    },
    {
      "date": "2025-04-09",
      "value": -1.209
    },
    {
      "date": "2025-04-10",
      "value": -0.777
    },
    {
      "date": "2025-04-11",
      "value": -1.156
    },
    {
      "date": "2025-04-14",
      "value": -1.025
    },
    {
      "date": "2025-04-15",
      "value": -0.439
    },
    {
      "date": "2025-04-16",
      "value": -0.796
    },
    {
      "date": "2025-04-17",
      "value": -1.13
    },
    {
      "date": "2025-04-21",
      "value": -1.828
    },
    {
      "date": "2025-04-22",
      "value": -1.807
    },
    {
      "date": "2025-04-23",
      "value": -1.521
    },
    {
      "date": "2025-04-24",
      "value": -1.521
    },
    {
      "date": "2025-04-25",
      "value": -1.812
    },
    {
      "date": "2025-04-28",
      "value": -1.518
    },
    {
      "date": "2025-04-29",
      "value": -1.845
    },
    {
      "date": "2025-04-30",
      "value": -1.993
    },
    {
      "date": "2025-05-01",
      "value": -1.75
    },
    {
      "date": "2025-05-02",
      "value": -2.263
    },
    {
      "date": "2025-05-05",
      "value": -1.878
    },
    {
      "date": "2025-05-06",
      "value": -2.213
    },
    {
      "date": "2025-05-07",
      "value": -2.484
    },
    {
      "date": "2025-05-08",
      "value": -1.953
    },
    {
      "date": "2025-05-09",
      "value": -2.275
    },
    {
      "date": "2025-05-12",
      "value": -2.747
    },
    {
      "date": "2025-05-13",
      "value": -2.605
    },
    {
      "date": "2025-05-14",
      "value": -3.195
    },
    {
      "date": "2025-05-15",
      "value": -2.62
    },
    {
      "date": "2025-05-16",
      "value": -2.353
    },
    {
      "date": "2025-05-19",
      "value": -1.43
    },
    {
      "date": "2025-05-20",
      "value": -1.449
    },
    {
      "date": "2025-05-21",
      "value": -1.831
    },
    {
      "date": "2025-05-22",
      "value": -2.181
    },
    {
      "date": "2025-05-23",
      "value": -1.859
    },
    {
      "date": "2025-05-27",
      "value": -1.873
    },
    {
      "date": "2025-05-28",
      "value": -1.742
    },
    {
      "date": "2025-05-29",
      "value": -2.208
    },
    {
      "date": "2025-05-30",
      "value": -2.009
    },
    {
      "date": "2025-06-02",
      "value": -1.966
    },
    {
      "date": "2025-06-03",
      "value": -2.018
    },
    {
      "date": "2025-06-04",
      "value": -2.087
    },
    {
      "date": "2025-06-05",
      "value": -2.173
    },
    {
      "date": "2025-06-06",
      "value": -2.078
    },
    {
      "date": "2025-06-09",
      "value": -1.944
    },
    {
      "date": "2025-06-10",
      "value": -1.773
    },
    {
      "date": "2025-06-11",
      "value": -1.52
    },
    {
      "date": "2025-06-12",
      "value": -1.349
    },
    {
      "date": "2025-06-13",
      "value": -1.293
    },
    {
      "date": "2025-06-16",
      "value": -1.077
    },
    {
      "date": "2025-06-17",
      "value": -0.861
    },
    {
      "date": "2025-06-18",
      "value": -1.464
    },
    {
      "date": "2025-06-20",
      "value": -1.529
    },
    {
      "date": "2025-06-23",
      "value": -1.492
    },
    {
      "date": "2025-06-24",
      "value": -1.4
    },
    {
      "date": "2025-06-25",
      "value": -1.124
    },
    {
      "date": "2025-06-26",
      "value": -1.503
    },
    {
      "date": "2025-06-27",
      "value": -1.68
    },
    {
      "date": "2025-06-30",
      "value": -1.817
    },
    {
      "date": "2025-07-01",
      "value": -1.427
    },
    {
      "date": "2025-07-02",
      "value": -1.331
    },
    {
      "date": "2025-07-03",
      "value": -1.264
    },
    {
      "date": "2025-07-07",
      "value": -1.11
    },
    {
      "date": "2025-07-08",
      "value": -1.613
    },
    {
      "date": "2025-07-09",
      "value": -1.153
    },
    {
      "date": "2025-07-10",
      "value": -1.127
    },
    {
      "date": "2025-07-11",
      "value": -1.38
    },
    {
      "date": "2025-07-14",
      "value": -1.256
    },
    {
      "date": "2025-07-15",
      "value": -0.676
    },
    {
      "date": "2025-07-16",
      "value": -0.654
    },
    {
      "date": "2025-07-17",
      "value": -0.645
    },
    {
      "date": "2025-07-18",
      "value": -0.807
    },
    {
      "date": "2025-07-21",
      "value": -0.897
    },
    {
      "date": "2025-07-22",
      "value": -0.889
    },
    {
      "date": "2025-07-23",
      "value": -1.158
    },
    {
      "date": "2025-07-24",
      "value": -0.947
    },
    {
      "date": "2025-07-25",
      "value": -0.42
    },
    {
      "date": "2025-07-28",
      "value": -0.048
    },
    {
      "date": "2025-07-29",
      "value": 0.047
    },
    {
      "date": "2025-07-30",
      "value": 0.152
    },
    {
      "date": "2025-07-31",
      "value": 0.132
    },
    {
      "date": "2025-08-01",
      "value": -0.222
    },
    {
      "date": "2025-08-04",
      "value": -0.214
    },
    {
      "date": "2025-08-05",
      "value": -0.211
    },
    {
      "date": "2025-08-06",
      "value": 1.674
    },
    {
      "date": "2025-08-07",
      "value": 1.882
    },
    {
      "date": "2025-08-08",
      "value": 1.622
    },
    {
      "date": "2025-08-11",
      "value": 1.683
    },
    {
      "date": "2025-08-12",
      "value": 1.044
    },
    {
      "date": "2025-08-13",
      "value": 1.129
    },
    {
      "date": "2025-08-14",
      "value": 1.109
    },
    {
      "date": "2025-08-15",
      "value": 0.917
    },
    {
      "date": "2025-08-18",
      "value": 0.804
    },
    {
      "date": "2025-08-19",
      "value": 0.729
    },
    {
      "date": "2025-08-20",
      "value": 0.522
    },
    {
      "date": "2025-08-21",
      "value": 0.868
    },
    {
      "date": "2025-08-22",
      "value": 0.732
    },
    {
      "date": "2025-08-25",
      "value": 0.029
    },
    {
      "date": "2025-08-26",
      "value": 0.99
    },
    {
      "date": "2025-08-27",
      "value": 0.026
    },
    {
      "date": "2025-08-28",
      "value": 0.357
    },
    {
      "date": "2025-08-29",
      "value": 1.163
    },
    {
      "date": "2025-09-02",
      "value": 0.98
    },
    {
      "date": "2025-09-03",
      "value": 1.21
    },
    {
      "date": "2025-09-04",
      "value": 0.253
    },
    {
      "date": "2025-09-05",
      "value": 0.609
    },
    {
      "date": "2025-09-08",
      "value": 0.863
    },
    {
      "date": "2025-09-09",
      "value": 0.696
    },
    {
      "date": "2025-09-10",
      "value": 0.484
    },
    {
      "date": "2025-09-11",
      "value": 0.702
    },
    {
      "date": "2025-09-12",
      "value": 0.813
    },
    {
      "date": "2025-09-15",
      "value": 0.446
    },
    {
      "date": "2025-09-16",
      "value": 0.365
    },
    {
      "date": "2025-09-17",
      "value": 0.283
    },
    {
      "date": "2025-09-18",
      "value": -0.845
    },
    {
      "date": "2025-09-19",
      "value": -1.188
    },
    {
      "date": "2025-09-22",
      "value": -1.142
    },
    {
      "date": "2025-09-23",
      "value": -1.167
    },
    {
      "date": "2025-09-24",
      "value": -1.337
    },
    {
      "date": "2025-09-25",
      "value": -0.735
    },
    {
      "date": "2025-09-26",
      "value": -1.281
    },
    {
      "date": "2025-09-29",
      "value": -1.933
    },
    {
      "date": "2025-09-30",
      "value": -1.62
    },
    {
      "date": "2025-10-01",
      "value": -0.98
    },
    {
      "date": "2025-10-02",
      "value": 0.136
    },
    {
      "date": "2025-10-03",
      "value": 0.625
    },
    {
      "date": "2025-10-06",
      "value": 0.244
    },
    {
      "date": "2025-10-07",
      "value": -0.27
    },
    {
      "date": "2025-10-08",
      "value": 0.991
    },
    {
      "date": "2025-10-09",
      "value": 1.344
    },
    {
      "date": "2025-10-10",
      "value": 1.913
    },
    {
      "date": "2025-10-13",
      "value": 1.465
    },
    {
      "date": "2025-10-14",
      "value": 1.757
    },
    {
      "date": "2025-10-15",
      "value": 1.721
    },
    {
      "date": "2025-10-16",
      "value": 2.179
    },
    {
      "date": "2025-10-17",
      "value": 1.449
    },
    {
      "date": "2025-10-20",
      "value": 1.256
    },
    {
      "date": "2025-10-21",
      "value": 0.809
    },
    {
      "date": "2025-10-22",
      "value": 1.451
    },
    {
      "date": "2025-10-23",
      "value": 1.357
    },
    {
      "date": "2025-10-24",
      "value": 1.396
    },
    {
      "date": "2025-10-27",
      "value": 1.548
    },
    {
      "date": "2025-10-28",
      "value": 0.719
    },
    {
      "date": "2025-10-29",
      "value": 0.713
    },
    {
      "date": "2025-10-30",
      "value": 1.394
    },
    {
      "date": "2025-10-31",
      "value": 1.442
    },
    {
      "date": "2025-11-03",
      "value": 1.705
    },
    {
      "date": "2025-11-04",
      "value": 2.745
    },
    {
      "date": "2025-11-05",
      "value": 2.15
    },
    {
      "date": "2025-11-06",
      "value": 2.175
    },
    {
      "date": "2025-11-07",
      "value": 1.689
    },
    {
      "date": "2025-11-10",
      "value": 1.171
    },
    {
      "date": "2025-11-11",
      "value": 1.149
    },
    {
      "date": "2025-11-12",
      "value": 1.023
    },
    {
      "date": "2025-11-13",
      "value": 1.223
    },
    {
      "date": "2025-11-14",
      "value": 1.516
    },
    {
      "date": "2025-11-17",
      "value": 1.559
    },
    {
      "date": "2025-11-18",
      "value": 1.466
    },
    {
      "date": "2025-11-19",
      "value": 1.451
    },
    {
      "date": "2025-11-20",
      "value": 1.093
    },
    {
      "date": "2025-11-21",
      "value": 1.116
    },
    {
      "date": "2025-11-24",
      "value": 0.742
    },
    {
      "date": "2025-11-25",
      "value": 0.735
    },
    {
      "date": "2025-11-26",
      "value": 0.831
    },
    {
      "date": "2025-11-28",
      "value": 0.354
    },
    {
      "date": "2025-12-01",
      "value": 0.008
    },
    {
      "date": "2025-12-02",
      "value": -0.423
    },
    {
      "date": "2025-12-03",
      "value": -0.593
    },
    {
      "date": "2025-12-04",
      "value": -0.774
    },
    {
      "date": "2025-12-05",
      "value": -0.024
    },
    {
      "date": "2025-12-08",
      "value": -0.098
    },
    {
      "date": "2025-12-09",
      "value": 0.774
    },
    {
      "date": "2025-12-10",
      "value": 0.878
    },
    {
      "date": "2025-12-11",
      "value": 0.381
    },
    {
      "date": "2025-12-12",
      "value": 1.434
    },
    {
      "date": "2025-12-15",
      "value": 1.012
    },
    {
      "date": "2025-12-16",
      "value": 1.533
    },
    {
      "date": "2025-12-17",
      "value": 1.697
    },
    {
      "date": "2025-12-18",
      "value": 0.901
    },
    {
      "date": "2025-12-19",
      "value": 0.63
    },
    {
      "date": "2025-12-22",
      "value": 0.449
    },
    {
      "date": "2025-12-23",
      "value": 0.506
    },
    {
      "date": "2025-12-24",
      "value": 0.503
    },
    {
      "date": "2025-12-26",
      "value": 0.274
    },
    {
      "date": "2025-12-29",
      "value": 0.012
    },
    {
      "date": "2025-12-30",
      "value": 0.187
    },
    {
      "date": "2025-12-31",
      "value": 0.339
    },
    {
      "date": "2026-01-02",
      "value": 0.527
    },
    {
      "date": "2026-01-05",
      "value": 0.55
    },
    {
      "date": "2026-01-06",
      "value": -0.17
    },
    {
      "date": "2026-01-07",
      "value": -0.223
    },
    {
      "date": "2026-01-08",
      "value": -0.239
    },
    {
      "date": "2026-01-09",
      "value": -0.511
    },
    {
      "date": "2026-01-12",
      "value": -0.555
    },
    {
      "date": "2026-01-13",
      "value": -0.735
    },
    {
      "date": "2026-01-14",
      "value": -1.143
    },
    {
      "date": "2026-01-15",
      "value": -0.963
    },
    {
      "date": "2026-01-16",
      "value": -0.547
    },
    {
      "date": "2026-01-20",
      "value": -0.96
    },
    {
      "date": "2026-01-21",
      "value": -0.865
    },
    {
      "date": "2026-01-22",
      "value": -0.874
    },
    {
      "date": "2026-01-23",
      "value": 0.337
    },
    {
      "date": "2026-01-26",
      "value": 1.062
    },
    {
      "date": "2026-01-27",
      "value": 0.986
    },
    {
      "date": "2026-01-28",
      "value": 1.462
    },
    {
      "date": "2026-01-29",
      "value": 1.587
    },
    {
      "date": "2026-01-30",
      "value": 0.564
    },
    {
      "date": "2026-02-02",
      "value": 0.047
    },
    {
      "date": "2026-02-03",
      "value": 0.11
    },
    {
      "date": "2026-02-04",
      "value": 1.063
    },
    {
      "date": "2026-02-05",
      "value": 1.015
    },
    {
      "date": "2026-02-06",
      "value": -0.481
    },
    {
      "date": "2026-02-09",
      "value": -0.38
    },
    {
      "date": "2026-02-10",
      "value": 0.457
    },
    {
      "date": "2026-02-11",
      "value": 0.151
    },
    {
      "date": "2026-02-12",
      "value": 0.471
    },
    {
      "date": "2026-02-13",
      "value": 0.429
    },
    {
      "date": "2026-02-17",
      "value": 0.454
    },
    {
      "date": "2026-02-18",
      "value": 0.238
    },
    {
      "date": "2026-02-19",
      "value": 0.315
    },
    {
      "date": "2026-02-20",
      "value": 0.973
    },
    {
      "date": "2026-02-23",
      "value": 1.182
    },
    {
      "date": "2026-02-24",
      "value": -0.173
    },
    {
      "date": "2026-02-25",
      "value": -0.946
    },
    {
      "date": "2026-02-26",
      "value": -0.417
    },
    {
      "date": "2026-02-27",
      "value": -0.259
    },
    {
      "date": "2026-03-02",
      "value": -0.22
    },
    {
      "date": "2026-03-03",
      "value": 0.148
    },
    {
      "date": "2026-03-04",
      "value": -0.052
    },
    {
      "date": "2026-03-05",
      "value": 0.058
    },
    {
      "date": "2026-03-06",
      "value": 0.389
    },
    {
      "date": "2026-03-09",
      "value": -0.164
    },
    {
      "date": "2026-03-10",
      "value": 0.126
    },
    {
      "date": "2026-03-11",
      "value": -0.122
    },
    {
      "date": "2026-03-12",
      "value": -0.073
    },
    {
      "date": "2026-03-13",
      "value": -0.163
    },
    {
      "date": "2026-03-16",
      "value": -0.558
    },
    {
      "date": "2026-03-17",
      "value": -0.23
    },
    {
      "date": "2026-03-18",
      "value": -0.347
    },
    {
      "date": "2026-03-19",
      "value": -1.019
    },
    {
      "date": "2026-03-20",
      "value": -0.882
    },
    {
      "date": "2026-03-23",
      "value": -0.788
    },
    {
      "date": "2026-03-24",
      "value": -0.875
    },
    {
      "date": "2026-03-25",
      "value": -1.026
    }
  ]
}