{
  "variant": "anchor_uptrend",
  "n_months": 272,
  "n_baskets": 44,
  "n_cash_months": 4,
  "cagr_lump_sum_pct": 42.50407686777351,
  "cagr_dca_pct": 41.99107232133428,
  "spy_lump_sum_pct": 11.09066804319685,
  "spy_dca_pct": 12.7099224937526,
  "edge_lump_sum_pp": 31.41340882457666,
  "edge_dca_pp": 29.281149827581675,
  "sharpe": 1.0997816834334266,
  "max_dd_pct": -48.53865522104518,
  "wf_mean_pct": 45.149128627780314,
  "wf_min_pct": 21.930909823811273,
  "wf_max_pct": 70.7997816637026,
  "wf_mean_edge_pp": 32.75830135464256,
  "wf_n_beat_spy": 10,
  "wf_n_positive": 10,
  "walk_forward": [
    {
      "split": "A1",
      "from": "2011-01-01",
      "to": "2018-12-31",
      "n_months": 96,
      "cagr_pct": 25.605273062884002,
      "spy_cagr_pct": 11.298712609873585,
      "edge_pp": 14.30656045301042,
      "sharpe": 0.966047649964771,
      "max_dd_pct": -33.15062351772803,
      "n_cash_months": 1
    },
    {
      "split": "A2",
      "from": "2015-01-01",
      "to": "2021-12-31",
      "n_months": 84,
      "cagr_pct": 39.39322646023247,
      "spy_cagr_pct": 14.827678919522679,
      "edge_pp": 24.565547540709787,
      "sharpe": 1.1357152780644966,
      "max_dd_pct": -31.898997779892156,
      "n_cash_months": 1
    },
    {
      "split": "A3",
      "from": "2018-01-01",
      "to": "2024-12-31",
      "n_months": 84,
      "cagr_pct": 53.61111449822202,
      "spy_cagr_pct": 13.719857315363914,
      "edge_pp": 39.89125718285811,
      "sharpe": 1.2740256307257052,
      "max_dd_pct": -31.898997779892156,
      "n_cash_months": 1
    },
    {
      "split": "R1_GFC",
      "from": "2008-01-01",
      "to": "2010-12-31",
      "n_months": 36,
      "cagr_pct": 65.69869907544077,
      "spy_cagr_pct": -2.78180889308145,
      "edge_pp": 68.48050796852222,
      "sharpe": 1.0373911700084721,
      "max_dd_pct": -36.38426118734397,
      "n_cash_months": 3
    },
    {
      "split": "R2",
      "from": "2011-01-01",
      "to": "2013-12-31",
      "n_months": 36,
      "cagr_pct": 37.60700010785216,
      "spy_cagr_pct": 16.07000308327717,
      "edge_pp": 21.536997024574987,
      "sharpe": 1.178151032367553,
      "max_dd_pct": -33.15062351772803,
      "n_cash_months": 0
    },
    {
      "split": "R3",
      "from": "2014-01-01",
      "to": "2016-12-31",
      "n_months": 36,
      "cagr_pct": 21.930909823811273,
      "spy_cagr_pct": 9.040352032995713,
      "edge_pp": 12.89055779081556,
      "sharpe": 1.0877792027646227,
      "max_dd_pct": -12.920970314971314,
      "n_cash_months": 0
    },
    {
      "split": "R4",
      "from": "2017-01-01",
      "to": "2019-12-31",
      "n_months": 36,
      "cagr_pct": 33.89087460096001,
      "spy_cagr_pct": 15.081113383528976,
      "edge_pp": 18.80976121743103,
      "sharpe": 1.1519912071395673,
      "max_dd_pct": -31.898997779892145,
      "n_cash_months": 1
    },
    {
      "split": "R5_COVID",
      "from": "2020-01-01",
      "to": "2022-12-31",
      "n_months": 36,
      "cagr_pct": 47.436623013286436,
      "spy_cagr_pct": 7.618476354813275,
      "edge_pp": 39.81814665847316,
      "sharpe": 1.0469187704853506,
      "max_dd_pct": -25.360733175253813,
      "n_cash_months": 0
    },
    {
      "split": "R6_AI",
      "from": "2023-01-01",
      "to": "2024-12-31",
      "n_months": 24,
      "cagr_pct": 70.7997816637026,
      "spy_cagr_pct": 25.529470848293222,
      "edge_pp": 45.270310815409374,
      "sharpe": 1.7559584035250382,
      "max_dd_pct": -14.406318025196851,
      "n_cash_months": 0
    },
    {
      "split": "STRICT",
      "from": "2021-01-01",
      "to": "2024-12-31",
      "n_months": 48,
      "cagr_pct": 55.51778397141136,
      "spy_cagr_pct": 13.504417076790375,
      "edge_pp": 42.01336689462099,
      "sharpe": 1.483265630155527,
      "max_dd_pct": -23.03637413527192,
      "n_cash_months": 0
    }
  ],
  "year_by_year": [
    {
      "year": 2003,
      "n_months": 4,
      "strat_ret_pct": 27.184886836439958,
      "spy_ret_pct": 10.641753408477195,
      "edge_pp": 16.543133427962765
    },
    {
      "year": 2004,
      "n_months": 12,
      "strat_ret_pct": 48.58164120999913,
      "spy_ret_pct": 10.697901694583356,
      "edge_pp": 37.88373951541577
    },
    {
      "year": 2005,
      "n_months": 12,
      "strat_ret_pct": 54.37129539957144,
      "spy_ret_pct": 4.828270027745751,
      "edge_pp": 49.54302537182569
    },
    {
      "year": 2006,
      "n_months": 12,
      "strat_ret_pct": 41.3911401133507,
      "spy_ret_pct": 15.845248842761016,
      "edge_pp": 25.54589127058968
    },
    {
      "year": 2007,
      "n_months": 12,
      "strat_ret_pct": 36.586409201036844,
      "spy_ret_pct": 5.14622542062535,
      "edge_pp": 31.44018378041149
    },
    {
      "year": 2008,
      "n_months": 12,
      "strat_ret_pct": 12.655731000083659,
      "spy_ret_pct": -36.79497208112278,
      "edge_pp": 49.450703081206434
    },
    {
      "year": 2009,
      "n_months": 12,
      "strat_ret_pct": 130.01979584099496,
      "spy_ret_pct": 26.351693261924545,
      "edge_pp": 103.66810257907039
    },
    {
      "year": 2010,
      "n_months": 12,
      "strat_ret_pct": 75.56534431491157,
      "spy_ret_pct": 15.056170358074228,
      "edge_pp": 60.509173956837344
    },
    {
      "year": 2011,
      "n_months": 12,
      "strat_ret_pct": 9.197191347952982,
      "spy_ret_pct": 1.8949508746777477,
      "edge_pp": 7.302240473275234
    },
    {
      "year": 2012,
      "n_months": 12,
      "strat_ret_pct": 9.344835800161476,
      "spy_ret_pct": 15.990369360273803,
      "edge_pp": -6.645533560112327
    },
    {
      "year": 2013,
      "n_months": 12,
      "strat_ret_pct": 118.22868546512795,
      "spy_ret_pct": 32.307782990064624,
      "edge_pp": 85.92090247506331
    },
    {
      "year": 2014,
      "n_months": 12,
      "strat_ret_pct": 16.186587712560872,
      "spy_ret_pct": 14.34687013535565,
      "edge_pp": 1.8397175772052243
    },
    {
      "year": 2015,
      "n_months": 12,
      "strat_ret_pct": 5.994914831103881,
      "spy_ret_pct": 1.2342672077436,
      "edge_pp": 4.760647623360281
    },
    {
      "year": 2016,
      "n_months": 12,
      "strat_ret_pct": 47.19749388741554,
      "spy_ret_pct": 11.997907724709055,
      "edge_pp": 35.19958616270649
    },
    {
      "year": 2017,
      "n_months": 12,
      "strat_ret_pct": 11.194985318792284,
      "spy_ret_pct": 21.705424517878,
      "edge_pp": -10.51043919908572
    },
    {
      "year": 2018,
      "n_months": 12,
      "strat_ret_pct": 17.954563934869782,
      "spy_ret_pct": -4.569001297783625,
      "edge_pp": 22.523565232653407
    },
    {
      "year": 2019,
      "n_months": 12,
      "strat_ret_pct": 83.00079826005057,
      "spy_ret_pct": 31.223845466663256,
      "edge_pp": 51.77695279338732
    },
    {
      "year": 2020,
      "n_months": 12,
      "strat_ret_pct": 59.834493962485034,
      "spy_ret_pct": 18.331634381392135,
      "edge_pp": 41.5028595810929
    },
    {
      "year": 2021,
      "n_months": 12,
      "strat_ret_pct": 70.83734056234239,
      "spy_ret_pct": 28.728770997528088,
      "edge_pp": 42.1085695648143
    },
    {
      "year": 2022,
      "n_months": 12,
      "strat_ret_pct": 17.3715425588,
      "spy_ret_pct": -18.175373553165997,
      "edge_pp": 35.546916111966
    },
    {
      "year": 2023,
      "n_months": 12,
      "strat_ret_pct": 115.98970377781788,
      "spy_ret_pct": 26.17579280754527,
      "edge_pp": 89.8139109702726
    },
    {
      "year": 2024,
      "n_months": 12,
      "strat_ret_pct": 35.06461144267055,
      "spy_ret_pct": 24.886459603923306,
      "edge_pp": 10.17815183874724
    },
    {
      "year": 2025,
      "n_months": 12,
      "strat_ret_pct": 12.899233186339366,
      "spy_ret_pct": 17.719061307023452,
      "edge_pp": -4.819828120684089
    },
    {
      "year": 2026,
      "n_months": 4,
      "strat_ret_pct": 0.0,
      "spy_ret_pct": 5.67553940227683,
      "edge_pp": -5.67553940227683
    }
  ]
}